[
{ "status" : "1", "seq" : "1", "start_ts" : "1643815504.263806", "resolve_ms" : "2.880096e-01", "connect_ms" : "6.560370e+01", "request_ms" : "1.032114e+00", "total_ms" : "9.517097e+01", "http_code" : "200", "msg" : "200 OK", "header_size" : "315", "data_size" : "0", "bps" : "0.000000", "host" : "50.116.32.37", "ssl_fingerprint" : "3f:55:f1:dd:5f:af:fd:ca:51:51:44:fb:26:a7:90:0c", "time_offset" : "-344.356537", "tfo_success" : "false", "ssl_ms" : "3.817511e-02", "tfo_succes" : "false", "ssl_ms" : "3.817511e-02", "write" : "2.820897e+01", "close" : "0.000000e+00", "cookies" : "0", "to" : "-3.443565e+02", "tcp_rtt_stats" : "2.761200e+01", "re_tx" : "0", "pmtu" : "1500", "tos" : "00" }
]
