[
{ "status" : "1", "seq" : "1", "start_ts" : "1632694705.313877", "resolve_ms" : "2.579689e-01", "connect_ms" : "4.506969e+01", "request_ms" : "4.911423e-01", "total_ms" : "6.238294e+01", "http_code" : "200", "msg" : "200 OK", "header_size" : "315", "data_size" : "0", "bps" : "0.000000", "host" : "50.116.32.37", "ssl_fingerprint" : "83:6b:1d:78:56:69:23:1e:e1:67:07:be:2c:2a:57:2c", "time_offset" : "-367.746353", "tfo_success" : "false", "ssl_ms" : "2.814102e-02", "tfo_succes" : "false", "ssl_ms" : "2.814102e-02", "write" : "1.653600e+01", "close" : "0.000000e+00", "cookies" : "0", "to" : "-3.677464e+02", "tcp_rtt_stats" : "1.679500e+01", "re_tx" : "0", "pmtu" : "1500", "tos" : "00" }
]
