[
{ "status" : "1", "seq" : "1", "start_ts" : "1643140435.945268", "resolve_ms" : "2.200603e-01", "connect_ms" : "1.311235e+02", "request_ms" : "1.481056e+00", "total_ms" : "1.944401e+02", "http_code" : "200", "msg" : "200 OK", "header_size" : "315", "data_size" : "0", "bps" : "0.000000", "host" : "50.116.32.37", "ssl_fingerprint" : "60:26:8f:db:69:a8:95:d3:e3:43:77:18:ce:d1:c2:38", "time_offset" : "-108.195066", "tfo_success" : "false", "ssl_ms" : "7.062793e-02", "tfo_succes" : "false", "ssl_ms" : "7.062793e-02", "write" : "6.154490e+01", "close" : "0.000000e+00", "cookies" : "0", "to" : "-1.081951e+02", "tcp_rtt_stats" : "6.063700e+01", "re_tx" : "0", "pmtu" : "1500", "tos" : "00" }
]
