[
{ "status" : "1", "seq" : "1", "start_ts" : "1631996334.164706", "resolve_ms" : "2.470016e-01", "connect_ms" : "6.552476e+01", "request_ms" : "9.429455e-01", "total_ms" : "9.472394e+01", "http_code" : "200", "msg" : "200 OK", "header_size" : "315", "data_size" : "0", "bps" : "0.000000", "host" : "50.116.32.37", "ssl_fingerprint" : "77:52:77:9e:0e:86:f1:8f:88:97:20:01:83:0a:00:d5", "time_offset" : "-244.972467", "tfo_success" : "false", "ssl_ms" : "3.725290e-02", "tfo_succes" : "false", "ssl_ms" : "3.725290e-02", "write" : "2.797198e+01", "close" : "0.000000e+00", "cookies" : "0", "to" : "-2.449725e+02", "tcp_rtt_stats" : "2.813200e+01", "re_tx" : "0", "pmtu" : "1500", "tos" : "00" }
]
