[
{ "status" : "1", "seq" : "1", "start_ts" : "1628771445.796681", "resolve_ms" : "1.771450e-01", "connect_ms" : "3.893964e+01", "request_ms" : "9.450912e-01", "total_ms" : "5.487919e+01", "http_code" : "200", "msg" : "200 OK", "header_size" : "315", "data_size" : "0", "bps" : "0.000000", "host" : "50.116.32.37", "ssl_fingerprint" : "77:52:77:9e:0e:86:f1:8f:88:97:20:01:83:0a:00:d5", "time_offset" : "-843.691587", "tfo_success" : "false", "ssl_ms" : "2.534986e-02", "tfo_succes" : "false", "ssl_ms" : "2.534986e-02", "write" : "1.479197e+01", "close" : "0.000000e+00", "cookies" : "0", "to" : "-8.436916e+02", "tcp_rtt_stats" : "1.374800e+01", "re_tx" : "0", "pmtu" : "1500", "tos" : "00" }
]
