[
{ "status" : "1", "seq" : "1", "start_ts" : "1626501112.525473", "resolve_ms" : "1.587868e-01", "connect_ms" : "1.322551e+02", "request_ms" : "6.909370e-01", "total_ms" : "1.959219e+02", "http_code" : "200", "msg" : "200 OK", "header_size" : "315", "data_size" : "0", "bps" : "0.000000", "host" : "50.116.32.37", "ssl_fingerprint" : "77:52:77:9e:0e:86:f1:8f:88:97:20:01:83:0a:00:d5", "time_offset" : "-689.676523", "tfo_success" : "false", "ssl_ms" : "7.099509e-02", "tfo_succes" : "false", "ssl_ms" : "7.099509e-02", "write" : "6.274605e+01", "close" : "0.000000e+00", "cookies" : "0", "to" : "-6.896765e+02", "tcp_rtt_stats" : "6.156900e+01", "re_tx" : "0", "pmtu" : "1500", "tos" : "00" }
]
