[
{ "status" : "1", "seq" : "1", "start_ts" : "1643591504.882444", "resolve_ms" : "2.779961e-01", "connect_ms" : "7.108216e+01", "request_ms" : "1.878977e+00", "total_ms" : "1.042371e+02", "http_code" : "200", "msg" : "200 OK", "header_size" : "315", "data_size" : "0", "bps" : "0.000000", "host" : "50.116.32.37", "ssl_fingerprint" : "60:26:8f:db:69:a8:95:d3:e3:43:77:18:ce:d1:c2:38", "time_offset" : "-970.263004", "tfo_success" : "false", "ssl_ms" : "4.096293e-02", "tfo_succes" : "false", "ssl_ms" : "4.096293e-02", "write" : "3.095698e+01", "close" : "0.000000e+00", "cookies" : "0", "to" : "-9.702630e+02", "tcp_rtt_stats" : "3.022900e+01", "re_tx" : "0", "pmtu" : "1500", "tos" : "00" }
]
