[
{ "status" : "1", "seq" : "1", "start_ts" : "1623653319.514484", "resolve_ms" : "2.009869e-01", "connect_ms" : "1.536671e+02", "request_ms" : "8.389950e-01", "total_ms" : "2.272151e+02", "http_code" : "200", "msg" : "200 OK", "header_size" : "315", "data_size" : "0", "bps" : "0.000000", "host" : "50.116.32.37", "ssl_fingerprint" : "77:52:77:9e:0e:86:f1:8f:88:97:20:01:83:0a:00:d5", "time_offset" : "-705.065966", "tfo_success" : "false", "ssl_ms" : "8.093095e-02", "tfo_succes" : "false", "ssl_ms" : "8.093095e-02", "write" : "7.242703e+01", "close" : "0.000000e+00", "cookies" : "0", "to" : "-7.050660e+02", "tcp_rtt_stats" : "7.241800e+01", "re_tx" : "0", "pmtu" : "1500", "tos" : "00" }
]
