[
{ "status" : "1", "seq" : "1", "start_ts" : "1625802636.725506", "resolve_ms" : "1.728535e-01", "connect_ms" : "1.358087e+02", "request_ms" : "3.259182e-01", "total_ms" : "1.995039e+02", "http_code" : "200", "msg" : "200 OK", "header_size" : "315", "data_size" : "0", "bps" : "0.000000", "host" : "50.116.32.37", "ssl_fingerprint" : "77:52:77:9e:0e:86:f1:8f:88:97:20:01:83:0a:00:d5", "time_offset" : "-893.285513", "tfo_success" : "false", "ssl_ms" : "7.343292e-02", "tfo_succes" : "false", "ssl_ms" : "7.343292e-02", "write" : "6.312299e+01", "close" : "0.000000e+00", "cookies" : "0", "to" : "-8.932855e+02", "tcp_rtt_stats" : "6.238200e+01", "re_tx" : "0", "pmtu" : "1500", "tos" : "00" }
]
