[
{ "status" : "1", "seq" : "1", "start_ts" : "1643613615.389592", "resolve_ms" : "2.090931e-01", "connect_ms" : "1.420875e+02", "request_ms" : "2.731085e+00", "total_ms" : "2.115121e+02", "http_code" : "200", "msg" : "200 OK", "header_size" : "315", "data_size" : "0", "bps" : "0.000000", "host" : "50.116.32.37", "ssl_fingerprint" : "60:26:8f:db:69:a8:95:d3:e3:43:77:18:ce:d1:c2:38", "time_offset" : "-566.534519", "tfo_success" : "false", "ssl_ms" : "7.650089e-02", "tfo_succes" : "false", "ssl_ms" : "7.650089e-02", "write" : "6.640792e+01", "close" : "0.000000e+00", "cookies" : "0", "to" : "-5.665345e+02", "tcp_rtt_stats" : "6.580400e+01", "re_tx" : "0", "pmtu" : "1500", "tos" : "00" }
]
