[
{ "status" : "1", "seq" : "1", "start_ts" : "1644481325.628246", "resolve_ms" : "2.758503e-01", "connect_ms" : "4.150824e+01", "request_ms" : "7.059574e-01", "total_ms" : "5.882382e+01", "http_code" : "200", "msg" : "200 OK", "header_size" : "315", "data_size" : "0", "bps" : "0.000000", "host" : "50.116.32.37", "ssl_fingerprint" : "3f:55:f1:dd:5f:af:fd:ca:51:51:44:fb:26:a7:90:0c", "time_offset" : "-678.563118", "tfo_success" : "false", "ssl_ms" : "2.594709e-02", "tfo_succes" : "false", "ssl_ms" : "2.594709e-02", "write" : "1.630783e+01", "close" : "0.000000e+00", "cookies" : "0", "to" : "-6.785631e+02", "tcp_rtt_stats" : "1.563800e+01", "re_tx" : "0", "pmtu" : "1500", "tos" : "00" }
]
