[
{ "status" : "1", "seq" : "1", "start_ts" : "1645185074.487775", "resolve_ms" : "2.129078e-01", "connect_ms" : "4.188763e+01", "request_ms" : "1.214199e+02", "total_ms" : "1.801908e+02", "http_code" : "200", "msg" : "200 OK", "header_size" : "349", "data_size" : "0", "bps" : "0.000000", "host" : "50.116.32.37", "ssl_fingerprint" : "72:22:19:73:99:94:f6:09:8a:db:a1:60:c7:ef:61:3e", "time_offset" : "-598.933935", "tfo_success" : "false", "ssl_ms" : "2.635884e-02", "tfo_succes" : "false", "ssl_ms" : "2.635884e-02", "write" : "1.664400e+01", "close" : "0.000000e+00", "cookies" : "0", "to" : "-5.989339e+02", "tcp_rtt_stats" : "1.567300e+01", "re_tx" : "0", "pmtu" : "1500", "tos" : "00" }
]
